zespa/__init__.py
zespa/configuration.py
zespa/github_requester.py
zespa/issue.py
zespa/main.py
zespa/zenhub_requester.py
zespa-0.1.2.dist-info/DESCRIPTION.rst
zespa-0.1.2.dist-info/METADATA
zespa-0.1.2.dist-info/RECORD
zespa-0.1.2.dist-info/WHEEL
zespa-0.1.2.dist-info/entry_points.txt
zespa-0.1.2.dist-info/metadata.json
zespa-0.1.2.dist-info/top_level.txt
