Metadata-Version: 2.0
Name: zespa
Version: 0.1.2
Summary: A tool to aggregate issues's story-point(estimate) by labels and time from ZenHub
Home-page: https://github.com/showwin/ZenHub-SP-Aggregator
Author: showwin
Author-email: showwin_kmc@yahoo.co.jp
License: Apache Software License
Keywords: ZenHub issue aggregate storypoint estimate
Platform: UNKNOWN
Classifier: Programming Language :: Python
Classifier: Programming Language :: Python :: 3.4
Classifier: Programming Language :: Python :: 3.5
Classifier: Programming Language :: Python :: 3.6
Classifier: Programming Language :: Python :: 3.7
Requires-Dist: beautifultable (==0.5.3)
Requires-Dist: fire (==0.1.2)
Requires-Dist: requests (>=2.20.0)
Requires-Dist: tqdm
